pyara/Model_weights.bin
pyara/__init__.py
pyara/alg_1_0.wav
pyara/alg_1_1.wav
pyara/audio_prepare.py
pyara/config.py
pyara/main.py
pyara/mozila11_0.wav
pyara/mozila11_1.wav
pyara/some.txt
pyara/Model/Model_weights.bin
pyara/Model/__init__.py
pyara/Model/model.py
src/__init__.py
src/pyara/__init__.py
src/pyara/audio_prepare.py
src/pyara/config.py
src/pyara/main.py
src/pyara/Model/__init__.py
src/pyara/Model/model.py
Pyara-1.0.6.dist-info/LICENSE
Pyara-1.0.6.dist-info/METADATA
Pyara-1.0.6.dist-info/WHEEL
Pyara-1.0.6.dist-info/top_level.txt
Pyara-1.0.6.dist-info/RECORD
