Metadata-Version: 2.1
Name: Pyara
Version: 1.0.6
Summary: Library for audio classification
Home-page: https://github.com/Millcool/Pyara.git
Author: Ilya Mironov, Pavel Aleksandrov
Author-email: ilyamironov210202@gmail.com
License: MIT
Platform: UNKNOWN
Classifier: Programming Language :: Python :: 3.7
Classifier: License :: OSI Approved :: GNU General Public License v3 (GPLv3)
Classifier: Operating System :: OS Independent
License-File: LICENSE
Requires-Dist: torch (>=1.13.1)
Requires-Dist: torchaudio (>=0.13.1)
Requires-Dist: soundfile (==0.12.1)
Requires-Dist: numpy
Requires-Dist: librosa
